deephelicon/__init__.py
deephelicon/load.py
deephelicon/predict.py
deephelicon/util/BPair.py
deephelicon/util/Console.py
deephelicon/util/DataInitializer.py
deephelicon/util/EVCouplingsModel.py
deephelicon/util/Fasta.py
deephelicon/util/FeatureS1.py
deephelicon/util/FeatureS2.py
deephelicon/util/Index.py
deephelicon/util/Irreflexive.py
deephelicon/util/Length.py
deephelicon/util/PFasta.py
deephelicon/util/Pair.py
deephelicon/util/Plmc.py
deephelicon/util/Position.py
deephelicon/util/Reader.py
deephelicon/util/Reformat.py
deephelicon/util/Segment.py
deephelicon/util/Separation.py
deephelicon/util/TMHMM.py
deephelicon/util/__init__.py
deephelicon/util/gdca.julia
deephelicon/util/troll.sh
deephelicon-0.0.1.dist-info/LICENSE
deephelicon-0.0.1.dist-info/METADATA
deephelicon-0.0.1.dist-info/WHEEL
deephelicon-0.0.1.dist-info/entry_points.txt
deephelicon-0.0.1.dist-info/RECORD
